lapa_database/__init__.py
lapa_database/configuration.py
lapa_database/create_database.py
lapa_database/main.py
lapa_database/data/config.ini
lapa_database/pydantic_models/__init__.py
lapa_database/pydantic_models/pydantic_models.py
lapa_database/utils/CommonOperations.py
lapa_database/utils/__init__.py
lapa_database/web_socket/Trigger.py
lapa_database/web_socket/WebsocketOperation.py
lapa_database/web_socket/__init__.py
lapa_database-0.0.14.dist-info/METADATA
lapa_database-0.0.14.dist-info/WHEEL
lapa_database-0.0.14.dist-info/top_level.txt
lapa_database-0.0.14.dist-info/RECORD
