Metadata-Version: 2.1
Name: lapa-database
Version: 0.0.14
Summary: database layer for my personal server.
Home-page: https://github.com/thepmsquare/lapa_database
Author: thePmSquare, Amish Palkar, Lav Sharma, Aaditya Sangsihetty
Author-email: thepmsquare@gmail.com, amishpalkar302001@gmail.com, lavsharma2016@gmail.com, adityashetty35@gmail.com
License: UNKNOWN
Platform: UNKNOWN
Classifier: Development Status :: 3 - Alpha
Classifier: Intended Audience :: Developers
Classifier: License :: OSI Approved :: MIT License
Classifier: Programming Language :: Python :: 3
Classifier: Programming Language :: Python :: 3.9
Requires-Dist: sqlalchemy >=2.0.23
Requires-Dist: psycopg2-binary >=2.9.9
Requires-Dist: uvicorn >=0.24.0.post1
Requires-Dist: fastapi >=0.104.1
Requires-Dist: python-multipart >=0.0.6
Requires-Dist: websockets >=12.0
Requires-Dist: httpx >=0.26.0
Requires-Dist: pytest >=8.0.0
Requires-Dist: square-logger >=1.0.0
Requires-Dist: lapa-commons >=0.0.3
Provides-Extra: all
Requires-Dist: lapa-database-structure >=0.0.1 ; extra == 'all'
